README.md
setup.py
csj_parser/__init__.py
csj_parser/csj.py
csj_parser.egg-info/PKG-INFO
csj_parser.egg-info/SOURCES.txt
csj_parser.egg-info/dependency_links.txt
csj_parser.egg-info/top_level.txt